acrolinx/__init__.py
acrolinx/client.py
acrolinx/core/__init__.py
acrolinx/core/api_error.py
acrolinx/core/client_wrapper.py
acrolinx/core/datetime_utils.py
acrolinx/core/file.py
acrolinx/core/force_multipart.py
acrolinx/core/http_client.py
acrolinx/core/http_response.py
acrolinx/core/jsonable_encoder.py
acrolinx/core/pydantic_utilities.py
acrolinx/core/query_encoder.py
acrolinx/core/remove_none_from_dict.py
acrolinx/core/request_options.py
acrolinx/core/serialization.py
acrolinx/environment.py
acrolinx/errors/__init__.py
acrolinx/errors/content_too_large_error.py
acrolinx/errors/forbidden_error.py
acrolinx/errors/internal_server_error.py
acrolinx/errors/not_found_error.py
acrolinx/errors/unprocessable_entity_error.py
acrolinx/py.typed
acrolinx/style_checks/__init__.py
acrolinx/style_checks/client.py
acrolinx/style_checks/raw_client.py
acrolinx/style_guides/__init__.py
acrolinx/style_guides/client.py
acrolinx/style_guides/raw_client.py
acrolinx/style_rewrites/__init__.py
acrolinx/style_rewrites/client.py
acrolinx/style_rewrites/raw_client.py
acrolinx/style_suggestions/__init__.py
acrolinx/style_suggestions/client.py
acrolinx/style_suggestions/raw_client.py
acrolinx/types/__init__.py
acrolinx/types/check_options.py
acrolinx/types/clarity_score.py
acrolinx/types/dialects.py
acrolinx/types/error_response.py
acrolinx/types/grammar_category.py
acrolinx/types/grammar_score.py
acrolinx/types/issue.py
acrolinx/types/issue_category.py
acrolinx/types/quality_score.py
acrolinx/types/rewrite_response.py
acrolinx/types/score_output.py
acrolinx/types/sentence_length_category.py
acrolinx/types/sentence_structure_category.py
acrolinx/types/simple_vocab_category.py
acrolinx/types/style_check_response.py
acrolinx/types/style_guide.py
acrolinx/types/style_guide_category.py
acrolinx/types/style_guide_response.py
acrolinx/types/style_guide_score.py
acrolinx/types/style_guide_status.py
acrolinx/types/style_guides.py
acrolinx/types/subcategory.py
acrolinx/types/suggestion.py
acrolinx_nextgen_api-0.0.4.dist-info/METADATA
acrolinx_nextgen_api-0.0.4.dist-info/WHEEL
acrolinx_nextgen_api-0.0.4.dist-info/RECORD
